timot-ben/__init__.py
timot-ben/src/__init__.py
timot-ben/src/ben.py
timot_ben/__init__.py
timot_ben/src/__init__.py
timot_ben/src/ben.py
timot_ben-0.0.3.dist-info/License.MD
timot_ben-0.0.3.dist-info/METADATA
timot_ben-0.0.3.dist-info/WHEEL
timot_ben-0.0.3.dist-info/top_level.txt
timot_ben-0.0.3.dist-info/RECORD
