Metadata-Version: 2.1
Name: timot_ben
Version: 0.0.3
Summary: My personal download module with my syntax
Home-page: https://github.com/timotofcourse/ben
Author: filmabemtv2@gmail.com
License: MIT
Classifier: License :: OSI Approved :: MIT License
Classifier: Programming Language :: Python :: 3.12
Classifier: Operating System :: OS Independent
Requires-Python: >=3.12
License-File: License.MD
Requires-Dist: requests
Requires-Dist: rich
